MANIFEST.in
README.md
logo_looper.svg
setup.cfg
setup.py
looper/__init__.py
looper/__main__.py
looper/_devtools.py
looper/_version.py
looper/conductor.py
looper/const.py
looper/exceptions.py
looper/html_reports.py
looper/looper.py
looper/parser_types.py
looper/pipeline_interface.py
looper/pipereqs.py
looper/project.py
looper/project_piface_group.py
looper/sample.py
looper/utils.py
looper/jinja_templates/footer.html
looper/jinja_templates/footer_index.html
looper/jinja_templates/head.html
looper/jinja_templates/index.html
looper/jinja_templates/logo.html
looper/jinja_templates/navbar.html
looper/jinja_templates/navbar_links.html
looper/jinja_templates/navbar_list_parent.html
looper/jinja_templates/object.html
looper/jinja_templates/project_object.html
looper/jinja_templates/sample.html
looper/jinja_templates/status.html
looper/jinja_templates/status_table.html
looper/jinja_templates/status_table_no_links.html
loopercli.egg-info/PKG-INFO
loopercli.egg-info/SOURCES.txt
loopercli.egg-info/dependency_links.txt
loopercli.egg-info/entry_points.txt
loopercli.egg-info/requires.txt
loopercli.egg-info/top_level.txt
requirements/requirements-all.txt
requirements/requirements-dev.txt
requirements/requirements-doc.txt
requirements/requirements-test.txt