Metadata-Version: 2.1
Name: loopercli
Version: 0.12.6
Summary: A pipeline submission engine that parses sample inputs and submits pipelines for each sample.
Home-page: https://github.com/pepkit/looper
Author: Nathan Sheffield, Vince Reuter, Michal Stolarczyk, Johanna Klughammer, Andre Rendeiro
License: BSD2
Keywords: bioinformatics,sequencing,ngs
Platform: UNKNOWN
Classifier: Development Status :: 4 - Beta
Classifier: License :: OSI Approved :: BSD License
Classifier: Programming Language :: Python :: 2.7
Classifier: Programming Language :: Python :: 3.5
Classifier: Programming Language :: Python :: 3.6
Classifier: Topic :: Scientific/Engineering :: Bio-Informatics
